apis_acdhch_django_auditlog/__init__.py
apis_acdhch_django_auditlog/apps.py
apis_acdhch_django_auditlog/urls.py
apis_acdhch_django_auditlog/views.py
apis_acdhch_django_auditlog/locale/de/LC_MESSAGES/django.po
apis_acdhch_django_auditlog/migrations/__init__.py
apis_acdhch_django_auditlog/templates/base.html
apis_acdhch_django_auditlog/templates/auditlog/logentry_list.html
apis_acdhch_django_auditlog-0.3.0.dist-info/METADATA
apis_acdhch_django_auditlog-0.3.0.dist-info/WHEEL
apis_acdhch_django_auditlog-0.3.0.dist-info/licenses/LICENSE
apis_acdhch_django_auditlog-0.3.0.dist-info/RECORD
